[{
    "postName": "Get Rich Slowly",
    "postContent": "Get Rich Slowly contains thousands of articles dedicated to boosting people's financial IQ.",
    "postAuthor": "Travis Mckie"
}, {
    "postName": "Get Rich ",
    "postContent": "We Are Already Rich to boosting people's financial IQ.",
    "postAuthor": "Antonio Reid"
}, {
    "postName": "Wheres the money ",
    "postContent": "Get Rich Slowly contains thousands of articles dedicated to boosting people's financial IQ.",
    "postAuthor": "Travis Mckie"
}, {
    "postName": "Wheres the money ",
    "postContent": "Get Rich Slowly contains thousands of articles dedicated to boosting people's financial IQ.",
    "postAuthor": "Travis Mckie"
}]